Workbook

Sheet Datos de entrada
A1: Tipo Usuario | B1: Potencia Contratada (kW) | C1: Potencia Contratada sugerida | D1: Potencia adoptada
A2: Pequeña Demanda Residencial (T1-R1, T1-R2 o T1-R3) | B2: 10 | C2: =+aux!I19 -> 0 | D2: =+aux!I20 -> 10
A4: Datos de consumo energético 12 meses anteriores | B4: Valores Ingresados app | C4: Valores sugeridos energia | D4: Valores adoptados
A5: Consumo mes 1 (kWh) | C5: =+aux!I4 -> 900 | D5: =+IF(B5<>"",B5,C5) -> 900
A6: Consumo mes 2 (kWh) | C6: =+aux!I5 -> 700 | D6: =+IF(B6<>"",B6,C6) -> 700
A7: Consumo mes 3 (kWh) | C7: =+aux!I6 -> 600 | D7: =+IF(B7<>"",B7,C7) -> 600
A8: Consumo mes 4 (kWh) | C8: =+aux!I7 -> 400 | D8: =+IF(B8<>"",B8,C8) -> 400
A9: Consumo mes 5 (kWh) | C9: =+aux!I8 -> 400 | D9: =+IF(B9<>"",B9,C9) -> 400
A10: Consumo mes 6 (kWh) | C10: =+aux!I9 -> 600 | D10: =+IF(B10<>"",B10,C10) -> 600
A11: Consumo mes 7 (kWh) | C11: =+aux!I10 -> 900 | D11: =+IF(B11<>"",B11,C11) -> 900
A12: Consumo mes 8 (kWh) | C12: =+aux!I11 -> 700 | D12: =+IF(B12<>"",B12,C12) -> 700
A13: Consumo mes 9 (kWh) | C13: =+aux!I12 -> 500 | D13: =+IF(B13<>"",B13,C13) -> 500
A14: Consumo mes 10 (kWh) | C14: =+aux!I13 -> 500 | D14: =+IF(B14<>"",B14,C14) -> 500
A15: Consumo mes 11 (kWh) | C15: =+aux!I14 -> 700 | D15: =+IF(B15<>"",B15,C15) -> 700
A16: Consumo mes 12 (kWh) | C16: =+aux!I15 -> 900 | D16: =+IF(B16<>"",B16,C16) -> 900
A17: Total consumo anual (kWh) | B17: =SUM(B5:B16) -> 0 | C17: =SUM(C5:C16) -> 7800 | D17: =SUM(D5:D16) -> 7800
A19: Datos de la Solar API
A20: yearlyEnergyDCkWh | B20: =C21/0.95 -> 3072.6316
A21: yearlyEnergyACkWh | B21: =B20*0.95 -> 2919 | C21: 2919 | D21: Energía Anual Generada App
A22: Número de paneles | B22: 4 | C22: =B24/1000*5*30*12 -> 2880 | D22: Verificación manual de la energía anual generada
A23: Capacidad paneles (W) | B23: 400
A24: Tamaño de la instalación (Wp) | B24: =B22*B23 -> 1600
A25: Emisiones de GEI
A26: Factor de emisión (KgCO2/MWh) | B26: 396.9995
A27: Factor de emisión (tCO2/MWh) | B27: =B26/1000 -> 0.3969995
A29: Cálculo manual
A30: Ahorros Económicos | B30: ='Eco-fin'!C4+'Eco-fin'!C5 -> 333.91967 | C30: USD-año
A31: Costo de Instalación | B31: ='Eco-fin'!B28 -> 2908.6814 | C31: USD
A32: Recupero de Inversión | B32: =ROUNDUP(Resultados!B16*12,0) -> 98 | C32: meses | D32: =B32/12 -> 8.1666667 | E32: años
A33: Potencia de la Instalación | B33: =('Datos de entrada'!B23*'Datos de entrada'!B22)/1000 -> 1.6 | C33: kW
A34: Energía Anual Generada | B34: ='Datos de entrada'!B21 -> 2919 | C34: kWh-año
A35: Superficie de Paneles | B35: =(1.879*1.045)*'Datos de entrada'!B22 -> 7.85422 | C35: m2
A36: Tarifas de Intercambio | B36: ='Eco-fin'!B12/'Eco-fin'!B8 -> 0.082039033 | C36: USD/kWh
A37: Emisiones de CO2 | B37: =Resultados!C19 -> 1.1588415 | C37: tCO2/año
A39: Resultados API
A40: Ahorros Económicos | B40: 762 | C40: =+B40/B30-1 -> 1.281986
A41: Costo de Instalación | B41: 7382 | C41: =+B41/B31-1 -> 1.5379197
A42: Recupero de Inversión | B42: 108 | C42: =+B42/B32-1 -> 0.10204082
A43: Potencia de la Instalación | C43: =+B43/B33-1 -> -1
A44: Energía Anual Generada | C44: =+B44/B34-1 -> -1
A45: Superficie de Paneles | C45: =+B45/B35-1 -> -1
A46: Tarifas de Intercambio | C46: =+B46/B36-1 -> -1
A47: Emisiones de CO2 | B47: 2.82 | C47: =+B47/B37-1 -> 1.4334647
A60: Nota: De la imagen mostrada se están ingresando los "Datos de la Solar API"
A78: Nota: De esta imagen se obtiene la cantidad equivalente de CO2 producida por MWh electricidad de la red ("carbonOffsetFactorKgPerMWh"). Esta es una medida de la intensidad de carbono de la electricidad de la red desplazada por la electricidad solar.

Sheet Medidor Bidireccional
A1: Costo Medidor Bidireccional Res 053/22 | B1: 54600 | C1: más IVA | D1: monto expresado al 30/10/21 | J1: Resolución EPRE Nº 053/22: RESUELVE, Inciso c) Se autoriza a las Distribuidoras a requerir de los usuarios como costo de provisión de los equipos de medición bidireccional para el registro de variables eléctricas en los suministros la suma de pesos CINCUENTA Y CUATRO MIL SEISCIENTOS CON 00/100 ($54.600,00), más IVA, monto expresado al 30/10/21, que se redeterminará en idéntica proporción a las variaciones que experimente la Base de Capital Regulatorio aprobada en cada Revisión Tarifaria Ordinaria o Extraordinaria. Energía San Juan S.A. y D.E.C.S.A., deberán presentar trimestralmente informes sustanciados detallando las características técnicas de los equipos adquiridos, el destino de los mismos, y todo otro dato de interés, correspondiendo la primera presentación en el plazo de quince (15) días de notificada la presente. En función de los Informes presentados y de los análisis que se realicen, este E.P.R.E. podrá modificar el valor autorizado.
A2: IVA | B2: 0.105
B4: Base de capital MM$ | C4: Fecha Res | D4: Variación | E4: Fecha | F4: Observaciones | G4: Costo medidor reexpresado
A5: Res 649/21 | B5: 15577.46 | C5: 44421 | D5: - | E5: Valor al 30/10/21 | F5: -
A6: Res 226/22 | B6: 19015.03 | C6: 44629 | D6: =+B6/$B$5-1 -> 0.2206759 | E6: Valor al 30/04/22 | F6: - | G6: =+$B$1*(1+D6) -> 66648.904 | H6: =+G6*(1+$B$2) -> 73647.039
A7: Res 717/22 | B7: 23734.69 | C7: 44777 | D7: =+B7/$B$5-1 -> 0.52365597 | E7: Valor al 31/10/22 | F7: índices proyectados | G7: =+$B$1*(1+D7) -> 83191.616 | H7: =+G7*(1+$B$2) -> 91926.736
A8: Res 152/23 | B8: 28395.87 | C8: 44966 | D8: =+B8/$B$5-1 -> 0.82288191 | E8: Valor al 31/10/22 | F8: índices publicados | G8: =+$B$1*(1+D8) -> 99529.352 | H8: =+G8*(1+$B$2) -> 109979.93
A9: Res 152/23 | B9: 37466.1 | C9: 44966 | D9: =+B9/$B$5-1 -> 1.4051482 | E9: Valor al 30/04/23 | F9: índices proyectados | G9: =+$B$1*(1+D9) -> 131321.09 | H9: =+G9*(1+$B$2) -> 145109.81
A10: Res 884/23 (5º RTE) | B10: 42495.16 | C10: 45168 | D10: =+B10/$B$5-1 -> 1.7279903 | E10: Valor al 30/04/23 | F10: índices publicados | G10: =+$B$1*(1+D10) -> 148948.27 | H10: =+G10*(1+$B$2) -> 164587.84
A11: Res 884/23 (5º RTE) | B11: 65627.83 | C11: 45168 | D11: =+B11/$B$5-1 -> 3.2129994 | E11: Valor al 31/10/23 | F11: índices proyectados | G11: =+$B$1*(1+D11) -> 230029.77 | H11: =+G11*(1+$B$2) -> 254182.89
A12: Res 085/24 | B12: 75343.75 | C12: 45315 | D12: =+B12/$B$5-1 -> 3.836716 | E12: Valor al 31/10/23 | F12: índices publicados | G12: =+$B$1*(1+D12) -> 264084.69 | H12: =+G12*(1+$B$2) -> 291813.59
A13: Res 085/24 | B13: 179474 | C13: 45315 | D13: =+B13/$B$5-1 -> 10.521391 | E13: Valor al 30/04/24 | F13: índices proyectados | G13: =+$B$1*(1+D13) -> 629067.92 | H13: =+G13*(1+$B$2) -> 695120.05 | I13: Nota ACC 1970/24
A14: Res 756/24 | B14: 171400 | C14: 45518 | D14: =+B14/$B$5-1 -> 10.003078 | E14: Valor al 30/04/24 | F14: índices publicados | G14: =+$B$1*(1+D14) -> 600768.03 | H14: =+G14*(1+$B$2) -> 663848.68
A15: Res 756/24 | B15: 244563 | C15: 45518 | D15: =+B15/$B$5-1 -> 14.6998 | E15: Valor al 31/10/24 | G15: =+$B$1*(1+D15) -> 857209.06 | H15: =+G15*(1+$B$2) -> 947216.01

Sheet Datos técnicos
A2: Caracteristicas del sistema FV
A3: Eficiencia instalacion (%) | B3: =+Parametros!B3 -> 0.8
A4: Degradación anual paneles (%) | B4: =+Parametros!B4 -> 0.004
A5: Factor de emisión (tCO2/MWh) | B5: ='Datos de entrada'!B27 -> 0.3969995
A6: Proporción de autoconsumo | B6: =+Parametros!B5 -> 0.8
A7: Proporción de inyección | B7: =1-B6 -> 0.2
A9: Tarifa asignada | B9: =+VLOOKUP('Datos de entrada'!A2,aux!$A$25:$B$32,2,0) -> T1-R
A10: MCSC Asignada | B10: =+aux!I20 -> 10
B13: =+'Eco-fin'!C3 -> 2027 | C13: =+'Eco-fin'!D3 -> 2028 | D13: =+'Eco-fin'!E3 -> 2029 | E13: =+'Eco-fin'!F3 -> 2030 | F13: =+'Eco-fin'!G3 -> 2031 | G13: =+'Eco-fin'!H3 -> 2032 | H13: =+'Eco-fin'!I3 -> 2033 | I13: =+'Eco-fin'!J3 -> 2034 | ... U13: =+'Eco-fin'!V3 -> 2046
A14: Generación fotovoltaica (kWh/año) | B14: ='Datos de entrada'!B21 -> 2919 | C14: =B14*(1-$B$4) -> 2907.324 | D14: =C14*(1-$B$4) -> 2895.6947 | E14: =D14*(1-$B$4) -> 2884.1119 | F14: =E14*(1-$B$4) -> 2872.5755 | G14: =F14*(1-$B$4) -> 2861.0852 | H14: =G14*(1-$B$4) -> 2849.6408 | I14: =H14*(1-$B$4) -> 2838.2423 | J14: =I14*(1-$B$4) -> 2826.8893 | ... U14: =T14*(1-$B$4) -> 2704.9642
B16: 2025 | C16: 2026 | D16: 2027 | E16: 2028 | F16: 2029 | G16: 2030 | H16: 2031 | I16: 2032 | J16: 2033 | K16: 2034 | L16: 2035 | M16: 2036 | N16: 2037 | O16: 2038 | P16: 2039 | Q16: 2040 | R16: 2041 | S16: 2042 | T16: 2043 | U16: 2044
A17: Energía Consumida (kWh/año) | B17: =+'Datos de entrada'!D17 -> 7800 | C17: =+B17 -> 7800 | D17: =+C17 -> 7800 | E17: =+D17 -> 7800 | F17: =+E17 -> 7800 | G17: =+F17 -> 7800 | H17: =+G17 -> 7800 | I17: =+H17 -> 7800 | J17: =+I17 -> 7800 | ... U17: =+T17 -> 7800
A18: Flujo de energia autoconsumida (kWh/año) | B18: =+IF(B17>B14*$B$6,B14*$B$6,B17) -> 2335.2 | C18: =+IF(C17>C14*$B$6,C14*$B$6,C17) -> 2325.8592 | D18: =+IF(D17>D14*$B$6,D14*$B$6,D17) -> 2316.5558 | E18: =+IF(E17>E14*$B$6,E14*$B$6,E17) -> 2307.2895 | F18: =+IF(F17>F14*$B$6,F14*$B$6,F17) -> 2298.0604 | G18: =+IF(G17>G14*$B$6,G14*$B$6,G17) -> 2288.8681 | H18: =+IF(H17>H14*$B$6,H14*$B$6,H17) -> 2279.7127 | I18: =+IF(I17>I14*$B$6,I14*$B$6,I17) -> 2270.5938 | ... U18: =+IF(U17>U14*$B$6,U14*$B$6,U17) -> 2163.9714
A19: Flujo de energía inyectada (kWh/año) | B19: =+B14-B18 -> 583.8 | C19: =+C14-C18 -> 581.4648 | D19: =+D14-D18 -> 579.13894 | E19: =+E14-E18 -> 576.82239 | F19: =+F14-F18 -> 574.5151 | G19: =+G14-G18 -> 572.21704 | H19: =+H14-H18 -> 569.92817 | I19: =+I14-I18 -> 567.64845 | ... U19: =+U14-U18 -> 540.99284
B21: 2025 | C21: 2026 | D21: 2027 | E21: 2028 | F21: 2029 | G21: 2030 | H21: 2031 | I21: 2032 | J21: 2033 | K21: 2034 | L21: 2035 | M21: 2036 | N21: 2037 | O21: 2038 | P21: 2039 | Q21: 2040 | R21: 2041 | S21: 2042 | T21: 2043 | U21: 2044
A22: Emisiones GEI evitadas (tCO2) | B22: =B14*$B$5/1000 -> 1.1588415 | C22: =C14*$B$5/1000 -> 1.1542062 | D22: =D14*$B$5/1000 -> 1.1495893 | E22: =E14*$B$5/1000 -> 1.144991 | F22: =F14*$B$5/1000 -> 1.140411 | G22: =G14*$B$5/1000 -> 1.1358494 | H22: =H14*$B$5/1000 -> 1.131306 | I22: =I14*$B$5/1000 -> 1.1267808 | ... U22: =U14*$B$5/1000 -> 1.0738694
C23: =+C22+B22 -> 2.3130477 | D23: =+C23+D22 -> 3.4626371 | E23: =+D23+E22 -> 4.6076281 | F23: =+E23+F22 -> 5.7480391 | G23: =+F23+G22 -> 6.8838885 | H23: =+G23+H22 -> 8.0151945 | I23: =+H23+I22 -> 9.1419752 | J23: =+I23+J22 -> 10.264249 | K23: =+J23+K22 -> 11.382033 | ... N23: =+M23+N22 -> 14.708632

Sheet Eco-fin
A2: Flujo de ingresos monetarios
B3: =+Resultados!B6 -> 2026 | C3: =+Resultados!C6 -> 2027 | D3: =+Resultados!D6 -> 2028 | E3: =+Resultados!E6 -> 2029 | F3: =+Resultados!F6 -> 2030 | G3: =+Resultados!G6 -> 2031 | H3: =+Resultados!H6 -> 2032 | I3: =+Resultados!I6 -> 2033 | ... V3: =+Resultados!V6 -> 2046
A4: Ahorro en factura electricidad total (USD) | C4: ='Datos técnicos'!B18*'Eco-fin'!C17*(1+'Eco-fin'!$B$22) -> 283.63056 | D4: ='Datos técnicos'!C18*'Eco-fin'!D17*(1+'Eco-fin'!$B$22) -> 296.62084 | E4: ='Datos técnicos'!D18*'Eco-fin'!E17*(1+'Eco-fin'!$B$22) -> 310.20608 | F4: ='Datos técnicos'!E18*'Eco-fin'!F17*(1+'Eco-fin'!$B$22) -> 324.41352 | G4: ='Datos técnicos'!F18*'Eco-fin'!G17*(1+'Eco-fin'!$B$22) -> 339.27165 | H4: ='Datos técnicos'!G18*'Eco-fin'!H17*(1+'Eco-fin'!$B$22) -> 354.8103 | I4: ='Datos técnicos'!H18*'Eco-fin'!I17*(1+'Eco-fin'!$B$22) -> 371.06061 | J4: ='Datos técnicos'!I18*'Eco-fin'!J17*(1+'Eco-fin'!$B$22) -> 388.05518 | ... V4: ='Datos técnicos'!U18*'Eco-fin'!V17*(1+'Eco-fin'!$B$22) -> 664.16676
A5: Ingresos por inyeccion de electricidad (USD) | C5: ='Datos técnicos'!B19*'Eco-fin'!C18 -> 50.289107 | D5: ='Datos técnicos'!C19*'Eco-fin'!D18 -> 52.592348 | E5: ='Datos técnicos'!D19*'Eco-fin'!E18 -> 55.001078 | F5: ='Datos técnicos'!E19*'Eco-fin'!F18 -> 57.520127 | G5: ='Datos técnicos'!F19*'Eco-fin'!G18 -> 60.154549 | H5: ='Datos técnicos'!G19*'Eco-fin'!H18 -> 62.909627 | I5: ='Datos técnicos'!H19*'Eco-fin'!I18 -> 65.790888 | J5: ='Datos técnicos'!I19*'Eco-fin'!J18 -> 68.804111 | ... V5: ='Datos técnicos'!U19*'Eco-fin'!V18 -> 117.76006
A6: Credito fiscal (USD) | C6: 0 | D6: 0 | E6: 0 | F6: 0 | G6: 0 | H6: 0 | I6: 0 | J6: 0 | K6: 0 | L6: 0 | M6: 0 | N6: 0 | O6: 0 | P6: 0 | Q6: 0 | R6: 0 | S6: 0 | T6: 0 | U6: 0 | V6: 0
A8: Tipo de cambio (ARS) | B8: =+Parametros!B17 -> 1510
A11: Cuadro tarifario
A12: Tarifas consumo de energía (ARS) | B12: =VLOOKUP('Datos técnicos'!B9,Parametros!$A$22:$D$29,2,FALSE()) -> 123.87894
A13: Tarifas inyección de energía (ARS) | B13: =VLOOKUP('Datos técnicos'!B9,Parametros!$A$22:$D$29,3,FALSE()) -> 123.87894
A15: Proyección de tarifas
B16: =+B3 -> 2026 | C16: =+C3 -> 2027 | D16: =+D3 -> 2028 | E16: =+E3 -> 2029 | F16: =+F3 -> 2030 | G16: =+G3 -> 2031 | H16: =+H3 -> 2032 | I16: =+I3 -> 2033 | ... V16: =+V3 -> 2046
A17: Cargo variable consumo (USD/kWh) | B17: =B12/B8 -> 0.082039033 | C17: =B17*(1+C19) -> 0.086140985 | D17: =C17*(1+D19) -> 0.090448034 | E17: =D17*(1+E19) -> 0.094970436 | F17: =E17*(1+F19) -> 0.099718957 | G17: =F17*(1+G19) -> 0.10470491 | H17: =G17*(1+H19) -> 0.10994015 | I17: =H17*(1+I19) -> 0.11543716 | J17: =I17*(1+J19) -> 0.12120902 | ... V17: =U17*(1+V19) -> 0.21767398
A18: Cargo variable inyección (USD/kWh) | B18: =B13/B8 -> 0.082039033 | C18: =B18*(1+C19) -> 0.086140985 | D18: =C18*(1+D19) -> 0.090448034 | E18: =D18*(1+E19) -> 0.094970436 | F18: =E18*(1+F19) -> 0.099718957 | G18: =F18*(1+G19) -> 0.10470491 | H18: =G18*(1+H19) -> 0.10994015 | I18: =H18*(1+I19) -> 0.11543716 | J18: =I18*(1+J19) -> 0.12120902 | ... V18: =U18*(1+V19) -> 0.21767398
A19: Tasa anual aumento de tarifas | C19: =+Parametros!B18 -> 0.05 | D19: =+C19 -> 0.05 | E19: =+D19 -> 0.05 | F19: =+E19 -> 0.05 | G19: =+F19 -> 0.05 | H19: =+G19 -> 0.05 | I19: =+H19 -> 0.05 | J19: =+I19 -> 0.05 | K19: =+J19 -> 0.05 | ... V19: =+U19 -> 0.05
A21: Otros impuestos
A22: Impuestos provinciales y tasas municipales | B22: =+Parametros!B35 -> 0.41
A24: Inversion y costos
B25: =+B16 -> 2026 | C25: =+C16 -> 2027 | D25: =+D16 -> 2028 | E25: =+E16 -> 2029 | F25: =+F16 -> 2030 | G25: =+G16 -> 2031 | H25: =+H16 -> 2032 | I25: =+I16 -> 2033 | ... V25: =+V16 -> 2046
A26: Costo (USD/Wp) | B26: =+Parametros!B9 -> 1.5
A27: Equipo de medición (USD) | B27: =+Parametros!B12 -> 508.68144
A28: Costo de inversión (USD) | B28: =B26*'Datos de entrada'!B24+B27 -> 2908.6814
A29: Costo de mantenimiento (USD) | B29: =+Parametros!B14 -> 29.086814 | C29: =+B29*(1+Parametros!$B$18) -> 30.541155 | D29: =+C29*(1+Parametros!$B$18) -> 32.068213 | E29: =+D29*(1+Parametros!$B$18) -> 33.671623 | F29: =+E29*(1+Parametros!$B$18) -> 35.355205 | G29: =+F29*(1+Parametros!$B$18) -> 37.122965 | H29: =+G29*(1+Parametros!$B$18) -> 38.979113 | I29: =+H29*(1+Parametros!$B$18) -> 40.928069 | J29: =+I29*(1+Parametros!$B$18) -> 42.974472 | ... V29: =+U29*(1+Parametros!$B$18) -> 77.175978

Sheet Resultados
A2: Flujo de fondos
A3: Tasa de descuento | B3: =+Parametros!B19 -> 0.05
A5: Caso con capital propio | B5: 0 | C5: =+B5+1 -> 1 | D5: =+C5+1 -> 2 | E5: =+D5+1 -> 3 | F5: =+E5+1 -> 4 | G5: =+F5+1 -> 5 | H5: =+G5+1 -> 6 | I5: =+H5+1 -> 7 | J5: =+I5+1 -> 8 | ... V5: =+U5+1 -> 20
B6: =+YEAR(TODAY()) -> 2026 | C6: =+B6+1 -> 2027 | D6: =+C6+1 -> 2028 | E6: =+D6+1 -> 2029 | F6: =+E6+1 -> 2030 | G6: =+F6+1 -> 2031 | H6: =+G6+1 -> 2032 | I6: =+H6+1 -> 2033 | J6: =+I6+1 -> 2034 | ... V6: =+U6+1 -> 2046
A7: Flujo de ingresos | C7: =SUM('Eco-fin'!C4:C6) -> 333.91967 | D7: =SUM('Eco-fin'!D4:D6) -> 349.21319 | E7: =SUM('Eco-fin'!E4:E6) -> 365.20715 | F7: =SUM('Eco-fin'!F4:F6) -> 381.93364 | G7: =SUM('Eco-fin'!G4:G6) -> 399.4262 | H7: =SUM('Eco-fin'!H4:H6) -> 417.71992 | I7: =SUM('Eco-fin'!I4:I6) -> 436.8515 | J7: =SUM('Eco-fin'!J4:J6) -> 456.85929 | ... V7: =SUM('Eco-fin'!V4:V6) -> 781.92683
A8: Flujo de egresos | C8: ='Eco-fin'!C29 -> 30.541155 | D8: ='Eco-fin'!D29 -> 32.068213 | E8: ='Eco-fin'!E29 -> 33.671623 | F8: ='Eco-fin'!F29 -> 35.355205 | G8: ='Eco-fin'!G29 -> 37.122965 | H8: ='Eco-fin'!H29 -> 38.979113 | I8: ='Eco-fin'!I29 -> 40.928069 | J8: ='Eco-fin'!J29 -> 42.974472 | ... V8: ='Eco-fin'!V29 -> 77.175978
A9: Inversiones | B9: ='Eco-fin'!B28 -> 2908.6814
A10: Flujo de fondos | B10: =B7-B8-B9 -> -2908.6814 | C10: =C7-C8-C9 -> 303.37851 | D10: =D7-D8-D9 -> 317.14498 | E10: =E7-E8-E9 -> 331.53553 | F10: =F7-F8-F9 -> 346.57844 | G10: =G7-G8-G9 -> 362.30324 | H10: =H7-H8-H9 -> 378.74081 | I10: =I7-I8-I9 -> 395.92343 | ... V10: =V7-V8-V9 -> 704.75085
A11: Flujo acumulado | B11: =B10 -> -2908.6814 | C11: =B11+C10 -> -2605.3029 | D11: =C11+D10 -> -2288.1579 | E11: =D11+E10 -> -1956.6224 | F11: =E11+F10 -> -1610.044 | G11: =F11+G10 -> -1247.7407 | H11: =G11+H10 -> -868.99993 | I11: =H11+I10 -> -473.0765 | J11: =I11+J10 -> -59.191677 | ... V11: =U11+V10 -> 6645.1887
A13: Indicadores financieros
A14: VAN | B14: =NPV(B3,C10:V10)+B10 -> 2633.966
A15: TIR | B15: =IRR(B10:V10) -> 0.12611884
A16: Pay Back Simple (años) | B16: {=LOOKUP(0,C11:V11,C5:V5+ABS(C11:V11)/D10:V10)} -> 8.1368087 | C16: =+B16*12 -> 97.641704
A18: Emisiones de GEI evitadas (tCO2) por año | B18: =+B6 -> 2026 | C18: =+C6 -> 2027 | D18: =+D6 -> 2028 | E18: =+E6 -> 2029 | F18: =+F6 -> 2030 | G18: =+G6 -> 2031 | H18: =+H6 -> 2032 | I18: =+I6 -> 2033 | ... V18: =+V6 -> 2046
C19: ='Datos técnicos'!B22 -> 1.1588415 | D19: ='Datos técnicos'!C22 -> 1.1542062 | E19: ='Datos técnicos'!D22 -> 1.1495893 | F19: ='Datos técnicos'!E22 -> 1.144991 | G19: ='Datos técnicos'!F22 -> 1.140411 | H19: ='Datos técnicos'!G22 -> 1.1358494 | I19: ='Datos técnicos'!H22 -> 1.131306 | J19: ='Datos técnicos'!I22 -> 1.1267808 | ... V19: ='Datos técnicos'!U22 -> 1.0738694

Sheet Parametros
A2: Caracteristicas del sistema FV
A3: Eficiencia instalacion (%) | B3: 0.8 | C3: no se utiliza (ver si es el que se usa en celda B21 datos de entrada)
A4: Degradación anual paneles (%) | B4: 0.004 | C4: anual
A5: Proporción de autoconsumo | B5: 0.8 | C5: es la proporción de energía generada que autoconsumo (hipótesis)
A7: Inversion y costos
A8: Costo (USD/Wp) CON IVA | B8: 1.5
A9: Costo (USD/Wp) aplicado | B9: =+IF('Datos de entrada'!A2="Pequeña Demanda Residencial (T1-R1, T1-R2 o T1-R3)",B8,B8/1.21) -> 1.5 | C9: incluye IVA para T1
A10: Equipo de medición ($AR) SIN IVA | B10: 695121.24 | C10: al 24/04/26
A11: IVA Equipo de medición | B11: 0.105
A12: Equipo de medición (USD) aplicado | B12: =+IF('Datos de entrada'!A2="Pequeña Demanda Residencial (T1-R1, T1-R2 o T1-R3)",(B10/B17)*(1+B11),B10/B17) -> 508.68144 | C12: =+C9 -> incluye IVA para T1
A13: Mantenimiento (% inversión inicial) | B13: 0.01
A14: Costo de mantenimiento inicial (USD/año) | B14: =+B13*'Eco-fin'!B28 -> 29.086814 | C14: =+C9 -> incluye IVA para T1
A16: Economicos
A17: Tipo de cambio (ARS) | B17: 1510 | C17: BNA cotiz. billete vendedor al 07/07/26
A18: Tasa inflación (en USD) | B18: 0.05 | C18: anual
A19: Tasa de descuento Flujo Fondos (USD) | B19: 0.05 | C19: anual
A21: Cuadro tarifario actual
A22: Tarifa | B22: Cargo variable consumo (ARS/kWh) (*) | C22: Cargo variable inyección (ARS/kWh) (*) | D22: Tensión
A23: T1-R | B23: 123.87894 | C23: =+B23 -> 123.87894 | D23: baja
A24: T1-G | B24: 130.54303 | C24: =+B24 -> 130.54303 | D24: baja
A25: T2-SMP | B25: 130.48055 | C25: =+B25 -> 130.48055 | D25: baja
A26: T2-CMP | B26: 130.47924 | C26: =+B26 -> 130.47924 | D26: baja
A27: T3-BT | B27: 130.43876 | C27: =+B27 -> 130.43876 | D27: baja
A28: T3-MT 13,2R | B28: 117.49303 | C28: =+B28 -> 117.49303 | D28: media
A29: TRA-SD | B29: 123.78791 | C29: =+B29 -> 123.78791 | D29: baja
A30: (*) Para el Caso de T3 y TRA se coloca el cargo Horas Resto
A32: Otros impuestos
A33: Impuestos y tasas provinciales | B33: 0.2
A34: IVA | B34: 0.21
A35: Total impuestos | B35: =+IF('Datos de entrada'!A2="Pequeña Demanda Residencial (T1-R1, T1-R2 o T1-R3)",B33+B34,B33) -> 0.41 | C35: incluye IVA para T1. Valor que toma la hoja "Eco-fin" para los cálculos

Sheet aux
I2: Elegido
A3: Consumos Mensuales | B3: T1-R | C3: T1-G | D3: T2-SMP | E3: T2-CMP | F3: T3-BT | G3: T3-MT 13,2R | H3: TRA-SD | I3: =+'Datos técnicos'!B9 -> T1-R | P3: T2-CMP | Q3: T3-BT | R3: T3-MT 13,2R | S3: TRA-SD
A4: 1 | B4: 900 | C4: 1600 | D4: 2700 | E4: =ROUND((E$17*P4/P$17)/100,0)*100 -> 1600 | F4: =ROUND((F$17*Q4/Q$17)/100,0)*100 -> 6000 | G4: =ROUND((G$17*R4/R$17)/100,0)*100 -> 7900 | H4: =ROUND((H$17*S4/S$17)/100,0)*100 -> 1300 | I4: =+HLOOKUP($I$3,$B$3:$H$15,A4+1,0) -> 900 | P4: 1.0473806e+08 | Q4: 1.4545379e+08 | R4: 2.4646714e+08 | S4: 1.2881077e+08
A5: 2 | B5: 700 | C5: 1300 | D5: 2600 | E5: =ROUND((E$17*P5/P$17)/100,0)*100 -> 2400 | F5: =ROUND((F$17*Q5/Q$17)/100,0)*100 -> 8500 | G5: =ROUND((G$17*R5/R$17)/100,0)*100 -> 10800 | H5: =ROUND((H$17*S5/S$17)/100,0)*100 -> 1500 | I5: =+HLOOKUP($I$3,$B$3:$H$15,A5+1,0) -> 700 | P5: 1.5129224e+08 | Q5: 2.0454221e+08 | R5: 3.3903423e+08 | S5: 1.5700196e+08
A6: 3 | B6: 600 | C6: 1300 | D6: 2500 | E6: =ROUND((E$17*P6/P$17)/100,0)*100 -> 2400 | F6: =ROUND((F$17*Q6/Q$17)/100,0)*100 -> 8900 | G6: =ROUND((G$17*R6/R$17)/100,0)*100 -> 11400 | H6: =ROUND((H$17*S6/S$17)/100,0)*100 -> 1400 | I6: =+HLOOKUP($I$3,$B$3:$H$15,A6+1,0) -> 600 | P6: 1.5150883e+08 | Q6: 2.1433515e+08 | R6: 3.5671253e+08 | S6: 1.4907168e+08
A7: 4 | B7: 400 | C7: 1000 | D7: 1900 | E7: =ROUND((E$17*P7/P$17)/100,0)*100 -> 2100 | F7: =ROUND((F$17*Q7/Q$17)/100,0)*100 -> 7800 | G7: =ROUND((G$17*R7/R$17)/100,0)*100 -> 9600 | H7: =ROUND((H$17*S7/S$17)/100,0)*100 -> 1200 | I7: =+HLOOKUP($I$3,$B$3:$H$15,A7+1,0) -> 400 | P7: 1.3261837e+08 | Q7: 1.8943737e+08 | R7: 3.0050626e+08 | S7: 1.2714498e+08
A8: 5 | B8: 400 | C8: 1100 | D8: 2100 | E8: =ROUND((E$17*P8/P$17)/100,0)*100 -> 2500 | F8: =ROUND((F$17*Q8/Q$17)/100,0)*100 -> 9400 | G8: =ROUND((G$17*R8/R$17)/100,0)*100 -> 11700 | H8: =ROUND((H$17*S8/S$17)/100,0)*100 -> 1200 | I8: =+HLOOKUP($I$3,$B$3:$H$15,A8+1,0) -> 400 | P8: 1.570316e+08 | Q8: 2.279129e+08 | R8: 3.6539436e+08 | S8: 1.2713513e+08
A9: 6 | B9: 600 | C9: 1200 | D9: 2300 | E9: =ROUND((E$17*P9/P$17)/100,0)*100 -> 2600 | F9: =ROUND((F$17*Q9/Q$17)/100,0)*100 -> 9800 | G9: =ROUND((G$17*R9/R$17)/100,0)*100 -> 11500 | H9: =ROUND((H$17*S9/S$17)/100,0)*100 -> 1000 | I9: =+HLOOKUP($I$3,$B$3:$H$15,A9+1,0) -> 600 | P9: 1.6810812e+08 | Q9: 2.3711692e+08 | R9: 3.5824765e+08 | S9: 1.0094112e+08
A10: 7 | B10: 900 | C10: 1200 | D10: 2200 | E10: =ROUND((E$17*P10/P$17)/100,0)*100 -> 2600 | F10: =ROUND((F$17*Q10/Q$17)/100,0)*100 -> 10000 | G10: =ROUND((G$17*R10/R$17)/100,0)*100 -> 11900 | H10: =ROUND((H$17*S10/S$17)/100,0)*100 -> 1100 | I10: =+HLOOKUP($I$3,$B$3:$H$15,A10+1,0) -> 900 | P10: 1.6408477e+08 | Q10: 2.4228342e+08 | R10: 3.7148791e+08 | S10: 1.1071089e+08
A11: 8 | B11: 700 | C11: 1100 | D11: 2200 | E11: =ROUND((E$17*P11/P$17)/100,0)*100 -> 2900 | F11: =ROUND((F$17*Q11/Q$17)/100,0)*100 -> 10700 | G11: =ROUND((G$17*R11/R$17)/100,0)*100 -> 13100 | H11: =ROUND((H$17*S11/S$17)/100,0)*100 -> 1600 | I11: =+HLOOKUP($I$3,$B$3:$H$15,A11+1,0) -> 700 | P11: 1.8242598e+08 | Q11: 2.5714405e+08 | R11: 4.1011457e+08 | S11: 1.6674017e+08
A12: 9 | B12: 500 | C12: 1100 | D12: 1900 | E12: =ROUND((E$17*P12/P$17)/100,0)*100 -> 3700 | F12: =ROUND((F$17*Q12/Q$17)/100,0)*100 -> 14600 | G12: =ROUND((G$17*R12/R$17)/100,0)*100 -> 15600 | H12: =ROUND((H$17*S12/S$17)/100,0)*100 -> 2500 | I12: =+HLOOKUP($I$3,$B$3:$H$15,A12+1,0) -> 500 | P12: 2.3806739e+08 | Q12: 3.5357392e+08 | R12: 4.8721303e+08 | S12: 2.5365754e+08
A13: 10 | B13: 500 | C13: 1200 | D13: 2000 | E13: =ROUND((E$17*P13/P$17)/100,0)*100 -> 3900 | F13: =ROUND((F$17*Q13/Q$17)/100,0)*100 -> 14900 | G13: =ROUND((G$17*R13/R$17)/100,0)*100 -> 16300 | H13: =ROUND((H$17*S13/S$17)/100,0)*100 -> 2800 | I13: =+HLOOKUP($I$3,$B$3:$H$15,A13+1,0) -> 500 | P13: 2.4714083e+08 | Q13: 3.5863948e+08 | R13: 5.1058304e+08 | S13: 2.8652249e+08
A14: 11 | B14: 700 | C14: 1500 | D14: 2500 | E14: =ROUND((E$17*P14/P$17)/100,0)*100 -> 4300 | F14: =ROUND((F$17*Q14/Q$17)/100,0)*100 -> 15200 | G14: =ROUND((G$17*R14/R$17)/100,0)*100 -> 16900 | H14: =ROUND((H$17*S14/S$17)/100,0)*100 -> 3000 | I14: =+HLOOKUP($I$3,$B$3:$H$15,A14+1,0) -> 700 | P14: 2.7262661e+08 | Q14: 3.6715573e+08 | R14: 5.2861542e+08 | S14: 3.1333887e+08
A15: 12 | B15: 900 | C15: 1900 | D15: 2300 | E15: =ROUND((E$17*P15/P$17)/100,0)*100 -> 4200 | F15: =ROUND((F$17*Q15/Q$17)/100,0)*100 -> 15500 | G15: =ROUND((G$17*R15/R$17)/100,0)*100 -> 16700 | H15: =ROUND((H$17*S15/S$17)/100,0)*100 -> 3200 | I15: =+HLOOKUP($I$3,$B$3:$H$15,A15+1,0) -> 900 | P15: 2.6802527e+08 | Q15: 3.7479379e+08 | R15: 5.2191404e+08 | S15: 3.3371162e+08
A16: TOTAL red | B16: =SUM(B4:B15) -> 7800 | C16: =SUM(C4:C15) -> 15500 | D16: =SUM(D4:D15) -> 27200 | E16: =SUM(E4:E15) -> 35200 | F16: =SUM(F4:F15) -> 131300 | G16: =SUM(G4:G15) -> 153400 | H16: =SUM(H4:H15) -> 21800 | I16: =SUM(I4:I15) -> 7800
A17: TOTAL calc fc | E17: =ROUND(E18*E20*24*365,0) -> 35040 | F17: =ROUND(F18*F20*24*365,0) -> 131400 | G17: =ROUND(G18*G20*24*365,0) -> 153300 | H17: =ROUND(H18*H20*24*365,0) -> 21900 | I17: =SUM(I4:I15) -> 7800 | P17: =SUM(P4:P15) -> 2.2376681e+09 | Q17: =SUM(Q4:Q15) -> 3.1723887e+09 | R17: =SUM(R4:R15) -> 4.7962902e+09 | S17: =SUM(S4:S15) -> 2.2547872e+09
A18: fc | E18: 0.2 | F18: 0.3 | G18: 0.35 | H18: 0.25
A19: Pot Max sugerida | E19: 25 | F19: 95 | G19: 155 | H19: 55 | I19: =+HLOOKUP($I$3,$B$3:$H$20,17,0) -> 0
A20: Pot Max asignada | B20: 10 | C20: 10 | D20: 20 | E20: =+MIN(MAX(IF('Datos de entrada'!$B$2<>0,'Datos de entrada'!$B$2,E19),E21),E22) -> 20 | F20: =+MIN(MAX(IF('Datos de entrada'!$B$2<>0,'Datos de entrada'!$B$2,F19),F21),F22) -> 50 | G20: =+MIN(MAX(IF('Datos de entrada'!$B$2<>0,'Datos de entrada'!$B$2,G19),G21),G22) -> 50 | H20: =+MIN(MAX(IF('Datos de entrada'!$B$2<>0,'Datos de entrada'!$B$2,H19),H21),H22) -> 10 | I20: =+HLOOKUP($I$3,$B$3:$H$20,18,0) -> 10
A21: Pot Max minima | E21: 20 | F21: 50 | G21: 50 | H21: 10
A22: Pot Max Maxima | E22: 50
A24: Tabla Tarifas
A25: Tipo Usuario | B25: Tarifa | K25: 906 | L25: 1630 | M25: 2720 | N25: =+ROUND(K25/100,0)*100 -> 900 | O25: =+ROUND(L25/100,0)*100 -> 1600 | P25: =+ROUND(M25/100,0)*100 -> 2700
A26: Pequeña Demanda Residencial (T1-R1, T1-R2 o T1-R3) | B26: T1-R | K26: 661 | L26: 1283 | M26: 2552 | N26: =+ROUND(K26/100,0)*100 -> 700 | O26: =+ROUND(L26/100,0)*100 -> 1300 | P26: =+ROUND(M26/100,0)*100 -> 2600
A27: Pequeña Demanda General (T1-G1, T1-G2 o T1-G3) | B27: T1-G | K27: 605 | L27: 1274 | M27: 2478 | N27: =+ROUND(K27/100,0)*100 -> 600 | O27: =+ROUND(L27/100,0)*100 -> 1300 | P27: =+ROUND(M27/100,0)*100 -> 2500
A28: Mediana Demanda sin Medición de Potencia (T2-SMP) | B28: T2-SMP | K28: 422 | L28: 982 | M28: 1867 | N28: =+ROUND(K28/100,0)*100 -> 400 | O28: =+ROUND(L28/100,0)*100 -> 1000 | P28: =+ROUND(M28/100,0)*100 -> 1900
A29: Mediana Demanda con Medición de Potencia (T2-CMP) | B29: T2-CMP | K29: 404 | L29: 1117 | M29: 2051 | N29: =+ROUND(K29/100,0)*100 -> 400 | O29: =+ROUND(L29/100,0)*100 -> 1100 | P29: =+ROUND(M29/100,0)*100 -> 2100
A30: Grande Demanda en Baja Tensión (T3-BT) | B30: T3-BT | K30: 564 | L30: 1227 | M30: 2333 | N30: =+ROUND(K30/100,0)*100 -> 600 | O30: =+ROUND(L30/100,0)*100 -> 1200 | P30: =+ROUND(M30/100,0)*100 -> 2300
A31: Grande Demanda en Media Tensión (T3-MT13,2 kV, T3-MT 33 kV) | B31: T3-MT 13,2R | K31: 879 | L31: 1201 | M31: 2222 | N31: =+ROUND(K31/100,0)*100 -> 900 | O31: =+ROUND(L31/100,0)*100 -> 1200 | P31: =+ROUND(M31/100,0)*100 -> 2200
A32: Riego Agrícola (TRA-SD) | B32: TRA-SD | K32: 679 | L32: 1083 | M32: 2165 | N32: =+ROUND(K32/100,0)*100 -> 700 | O32: =+ROUND(L32/100,0)*100 -> 1100 | P32: =+ROUND(M32/100,0)*100 -> 2200
K33: 467 | L33: 1060 | M33: 1880 | N33: =+ROUND(K33/100,0)*100 -> 500 | O33: =+ROUND(L33/100,0)*100 -> 1100 | P33: =+ROUND(M33/100,0)*100 -> 1900
K34: 490 | L34: 1185 | M34: 2044 | N34: =+ROUND(K34/100,0)*100 -> 500 | O34: =+ROUND(L34/100,0)*100 -> 1200 | P34: =+ROUND(M34/100,0)*100 -> 2000
K35: 703 | L35: 1544 | M35: 2522 | N35: =+ROUND(K35/100,0)*100 -> 700 | O35: =+ROUND(L35/100,0)*100 -> 1500 | P35: =+ROUND(M35/100,0)*100 -> 2500
K36: 883 | L36: 1911 | M36: 2315 | N36: =+ROUND(K36/100,0)*100 -> 900 | O36: =+ROUND(L36/100,0)*100 -> 1900 | P36: =+ROUND(M36/100,0)*100 -> 2300
